dc_agent_cards/__init__.py
dc_agent_cards/controllers/agent_controller.py
dc_agent_cards/controllers/conversations_router.py
dc_agent_cards/controllers/open_router.py
dc_agent_cards/models/conversation_models.py
dc_agent_cards/models/conversations_classes.py
dc_agent_cards/services/conversation_agents.py
dc_agent_cards/services/groq_utils.py
dc_agent_cards/services/pydantic_agent_service.py
dataclouder_agent_cards-0.0.14.dist-info/METADATA
dataclouder_agent_cards-0.0.14.dist-info/WHEEL
dataclouder_agent_cards-0.0.14.dist-info/RECORD
